kwslib/__init__.py
kwslib/client.py
kwslib/minio_client.py
kwslib/telegram_notifier.py
kwslib/api/__init__.py
kwslib/api/admin.py
kwslib/api/artifacts.py
kwslib/api/audio.py
kwslib/api/auth.py
kwslib/api/base.py
kwslib/api/collection.py
kwslib/api/compare.py
kwslib/api/config.py
kwslib/api/dashboard.py
kwslib/api/dataset_splits.py
kwslib/api/datasets.py
kwslib/api/deployed_models.py
kwslib/api/devices.py
kwslib/api/embeddings.py
kwslib/api/experiments.py
kwslib/api/features.py
kwslib/api/fewshot.py
kwslib/api/jobs.py
kwslib/api/keywords.py
kwslib/api/metadata.py
kwslib/api/metrics.py
kwslib/api/models.py
kwslib/api/notifications.py
kwslib/api/predict.py
kwslib/api/quality_control.py
kwslib/api/recordings.py
kwslib/api/reward_payout.py
kwslib/api/sentences.py
kwslib/api/tasks.py
kwslib/api/users.py
kwslib/api/visualize.py
kwslib-0.0.2.dist-info/METADATA
kwslib-0.0.2.dist-info/WHEEL
kwslib-0.0.2.dist-info/top_level.txt
kwslib-0.0.2.dist-info/RECORD
